{
    "generated": "2026-07-22 13:06:06.640917",
    "summary": {
        "total_runs": 1,
        "average_quality": 10.0,
        "average_coverage": 0.0,
        "average_pylint": 0.0,
        "security_errors": 0
    },
    "history": [
        {
            "run": 67,
            "date": "2026-07-22T13:06:06.637938",
            "branch": "main",
            "commit": "c1d6d5eab79e5cc212376a6b1344487a20c1cc1e",
            "status": "success",
            "quality": 10.0,
            "coverage": 0,
            "pylint": 0,
            "complexity": 0,
            "tests": {
                "total": 0,
                "passed": 0,
                "failed": 0,
                "skipped": 0,
                "duration": 0
            },
            "security": {
                "high": 0,
                "medium": 0,
                "low": 0
            },
            "documentation": {
                "score": 0,
                "details": {}
            }
        }
    ]
}